<?xml version="1.0" encoding="UTF-8"?>
<EasyForm Name="PictureNewForm" Class="PictureForm" Icon="{RESOURCE_URL}/picture/images/icon_picture.png" FormType="New" jsClass="jbForm" Title="New Picture" Description="Please select files from your computer to upload pictures." BizDataObj="picture.do.PicturePickDO" PageSize="10" DefaultForm="Y" TemplateEngine="Smarty" TemplateFile="form_picture_quick_add.tpl.html"  Access="picture.access">
    <DataPanel>        
        <Element Name="fld_title" DefaultValue="New Picture" Class="InputText" FieldName="title" Label="Title"   />	
        <Element Name="fld_pictures" Class="picture.element.PictureUploader" FieldName="file" Label="Files" />
    </DataPanel>
    <ActionPanel>
	    <Element Name="btn_upload_file" Class="Hidden" >
            <EventHandler Name="upload_onclick" EventLogMsg="" Event="onclick" Function="uploadFile()"  />
        </Element>
        <Element Name="btn_check_file" Class="Hidden" >
            <EventHandler Name="check_onclick" EventLogMsg="" Event="onclick" Function="checkFile()"  />
        </Element> 
        <Element Name="btn_upload" Class="Button" Text="Upload" CssClass="button_gray_m">
            <EventHandler Name="save_onclick" EventLogMsg="" Event="onclick" Function="js:$j('#fld_pictures').uploadifyUpload()"   ShortcutKey="Ctrl+Enter" ContextMenu="Save" />
        </Element>        
        <Element Name="btn_clear" Class="Button" Text="Clear" CssClass="button_gray_m">
            <EventHandler Name="btn_clear_onclick" Event="onclick" Function="js:$j('#fld_pictures').uploadifyClearQueue()"/>
        </Element>
        <Element Name="Spacer" Class="Spacer" Width="10" />
        <Element Name="btn_close" Class="Button" Text="Close" CssClass="button_gray_m">
            <EventHandler Name="btn_close_onclick" Event="onclick" Function="js:Openbiz.Window.closeDialog()"/>
        </Element>
    </ActionPanel> 
    <NavPanel>
    </NavPanel> 
    <SearchPanel>
    </SearchPanel>
</EasyForm>