<?xml version="1.0" standalone="no"?>
<Upgrade>
    <Version Name="0.92">
        <UpgradeSql><![CDATA[
DROP TABLE IF EXISTS `task_billing`;
DROP TABLE IF EXISTS `task_budget`;
CREATE TABLE `task_budget` (
  `id` int(11) NOT NULL auto_increment,
  `type` varchar(255) default '',
  `foreign_id` int(11) NOT NULL,
  `title` varchar(255) default '',
  `description` text NOT NULL,  
  `credit` float(11) NOT NULL,
  `debit` float(11) NOT NULL,
  `create_by` int(11) NOT NULL,
  `create_time` datetime NOT NULL,
  `update_by` int(11) NOT NULL,
  `update_time` timestamp NOT NULL default '0000-00-00 00:00:00' on update CURRENT_TIMESTAMP,
  PRIMARY KEY  (`id`)
) ENGINE=MyISAM DEFAULT CHARSET=utf8;
        ]]></UpgradeSql>
    </Version>
    <Version Name="0.95">
        <UpgradeSql><![CDATA[

SET FOREIGN_KEY_CHECKS=0;
DROP TABLE IF EXISTS `project_type`;
CREATE TABLE `project_type` (
  `id` int(11) NOT NULL AUTO_INCREMENT,
  `name` varchar(255) NOT NULL,
  `description` text NOT NULL,
  `color` varchar(255) NOT NULL,
  `sortorder` int(11) NOT NULL,
  `published` int(11) NOT NULL,
  `group_id` INT(11) default '1',
  `group_perm` INT(11) default '1',
  `other_perm` INT(11) default '1' ,
  `create_by` int(11) NOT NULL,
  `create_time` datetime NOT NULL,
  `update_by` int(11) NOT NULL,
  `update_time` timestamp NOT NULL DEFAULT CURRENT_TIMESTAMP ON UPDATE CURRENT_TIMESTAMP,
  PRIMARY KEY  (`id`)
) ENGINE=MyISAM AUTO_INCREMENT=1 DEFAULT CHARSET=utf8;

INSERT INTO `project_type` (`id`, `name`, `color`,`description`, `sortorder`, `published`, `create_by`, `create_time`, `update_by`, `update_time`) VALUES
(1, 'Business', '66c2ff', 'Business Contacts', 45, 1, 1, '2010-05-23 01:09:06', 1, '2010-05-23 18:47:14'),
(2, 'Family', 'ff7aa0', 'Family Contacts', 45, 1, 1, '2010-05-23 01:23:04', 1, '2010-05-24 18:51:35'),
(3, 'Provider', '7fff7f', 'Business Provider Contacts', 50, 1, 1, '2010-05-23 01:34:12', 1, '2010-05-24 02:41:09'),
(4, 'Client', 'ffd042','Business Client Contacts', 45, 1, 1, '2010-05-23 01:34:39', 1, '2010-05-24 11:10:32');

DROP TABLE IF EXISTS `project`;
CREATE TABLE `project` (
`id` int(11) NOT NULL auto_increment,
`name` VARCHAR( 255 ) NOT NULL ,
`description` TEXT NOT NULL ,
`start_time` DATETIME NOT NULL ,
`type_id` INT NOT NULL DEFAULT '1',
`budget_cost` float(11) NOT NULL,
`status` int(11) NOT NULL,
`priority` int(11) NOT NULL,
`sortorder` int(11) NOT NULL,
`owner_id` int(11) default 0,
`group_id` INT(11) default '1',
`group_perm` INT(11) default '1',
`other_perm` INT(11) default '1' ,
`create_by` INT NOT NULL ,
`create_time` DATETIME NOT NULL ,
`update_by` INT NOT NULL ,
`update_time` DATETIME NOT NULL ,
PRIMARY KEY ( `id` ) ,
INDEX ( `name` , `type_id` )
) ENGINE=MyISAM AUTO_INCREMENT=1 DEFAULT CHARSET=utf8;


DROP TABLE IF EXISTS `project_contact`;
CREATE TABLE `project_contact` (
  `id` int(10) unsigned NOT NULL auto_increment,
  `project_id` int(10) unsigned NOT NULL default '0',
  `contact_id` int(10) unsigned NOT NULL default '0',
  PRIMARY KEY  (`id`),
  KEY `project_id` (`project_id`),
  KEY `contact_id` (`contact_id`)
) ENGINE=MyISAM DEFAULT CHARSET=utf8;

DROP TABLE IF EXISTS `project_event`;
CREATE TABLE `project_event` (
  `id` int(10) unsigned NOT NULL auto_increment,
  `project_id` int(10) unsigned NOT NULL default '0',
  `event_id` int(10) unsigned NOT NULL default '0',
  PRIMARY KEY  (`id`),
  KEY `project_id` (`project_id`),
  KEY `event_id` (`event_id`)
) ENGINE=MyISAM DEFAULT CHARSET=utf8;
        ]]></UpgradeSql>
       </Version>
       <Version Name="1.0.0">
        <UpgradeSQL>
        <![CDATA[
DROP TABLE IF EXISTS `project_template`;
CREATE TABLE `project_template` (
`id` int(10) unsigned NOT NULL auto_increment,
`name` VARCHAR( 255 ) NOT NULL ,
`description` TEXT NOT NULL ,
`type_id` int(11) NOT NULL,
`sortorder` int(11) NOT NULL,
`group_id` INT(11) default '1',
`group_perm` INT(11) default '1',
`other_perm` INT(11) default '1' ,
`create_by` INT NOT NULL ,
`create_time` DATETIME NOT NULL ,
`update_by` INT NOT NULL ,
`update_time` DATETIME NOT NULL ,
PRIMARY KEY ( `id` ) ,
INDEX ( `name` , `type_id` )
) ENGINE = MYISAM CHARACTER SET utf8 COLLATE utf8_general_ci ;

DROP TABLE IF EXISTS `project_task_template`;
CREATE TABLE `project_task_template` (
  `id` int(11) NOT NULL auto_increment,
  `title` varchar(255) default '',
  `description` text NOT NULL,
  `priority` int(11) NOT NULL,
  `milestone` int(11) NOT NULL,
  `start_date` int(11) NOT NULL,
  `during_days` int(11) NOT NULL,
  `budget_cost` float(11) NOT NULL,
  `project_id` int(11) default 0,
  `parent_task_id` int(11) default 0,
  `dependency_task_id` int(11) default 0,
  `type_id` int(11) NOT NULL,
  `create_by` int(11) NOT NULL,
  `create_time` datetime NOT NULL,
  `update_by` int(11) NOT NULL,
  `update_time` timestamp NOT NULL default '0000-00-00 00:00:00' on update CURRENT_TIMESTAMP,
  PRIMARY KEY  (`id`)
) ENGINE=MyISAM DEFAULT CHARSET=utf8;        
        ]]>
        </UpgradeSQL>
        
    </Version>
    <Version Name="1.0.1">
        <UpgradeSql><![CDATA[
ALTER TABLE `task` ADD `severity` INT NOT NULL DEFAULT '2' AFTER `priority`;  
ALTER TABLE `project_task_template` ADD `severity` INT NOT NULL DEFAULT '2' AFTER `priority`;
ALTER TABLE `project` ADD `condition` INT NULL DEFAULT '0' AFTER `priority`;
        ]]></UpgradeSql>
    </Version>
    <Version Name="1.1.4">
        <UpgradeSql><![CDATA[
DROP TABLE IF EXISTS `work_log_event`;
CREATE TABLE `work_log_event` (
  `id` int(10) unsigned NOT NULL auto_increment,
  `worklog_id` int(10) unsigned NOT NULL default '0',
  `event_id` int(10) unsigned NOT NULL default '0',
  PRIMARY KEY  (`id`),
  KEY `worklog_id` (`worklog_id`),
  KEY `event_id` (`event_id`)
) ENGINE=MyISAM DEFAULT CHARSET=utf8;


DROP TABLE IF EXISTS `work_log_document`;
CREATE TABLE `work_log_document` (
  `id` int(10) unsigned NOT NULL auto_increment,
  `worklog_id` int(10) unsigned NOT NULL default '0',
  `document_id` int(10) unsigned NOT NULL default '0',
  PRIMARY KEY  (`id`),
  KEY `worklog_id` (`worklog_id`),
  KEY `document_id` (`document_id`)
) ENGINE=MyISAM DEFAULT CHARSET=utf8;

        ]]></UpgradeSql>
    </Version>   
    <Version Name="1.1.6">
        <UpgradeSql><![CDATA[
    DROP TABLE IF EXISTS `task_document`;
CREATE TABLE `task_document` (
  `id` int(10) unsigned NOT NULL auto_increment,
  `task_id` int(10) unsigned NOT NULL default '0',
  `document_id` int(10) unsigned NOT NULL default '0',
  PRIMARY KEY  (`id`),
  KEY `task_id` (`task_id`),
  KEY `document_id` (`document_id`)
) ENGINE=MyISAM DEFAULT CHARSET=utf8;
        ]]></UpgradeSql>
    </Version>      

    <Version Name="1.3">
        <UpgradeSql><![CDATA[
DROP TABLE IF EXISTS `document_related`;
CREATE TABLE `document_related` (
  `id` int(10) unsigned NOT NULL auto_increment,
  `document_id` int(10) unsigned NOT NULL default '0',
  `related_id` int(10) unsigned NOT NULL default '0',  
  PRIMARY KEY  (`id`),
  KEY `related_id` (`related_id`),
  KEY `document_id` (`document_id`)
) ENGINE=MyISAM DEFAULT CHARSET=utf8;

DROP TABLE IF EXISTS `event_related`;
CREATE TABLE `event_related` (
  `id` int(10) unsigned NOT NULL auto_increment,
  `event_id` int(10) unsigned NOT NULL default '0',
  `related_id` int(10) unsigned NOT NULL default '0',  
  PRIMARY KEY  (`id`),
  KEY `related_id` (`related_id`),
  KEY `event_id` (`event_id`)
) ENGINE=MyISAM DEFAULT CHARSET=utf8;

DROP TABLE IF EXISTS `task_related`;
CREATE TABLE `task_related` (
  `id` int(10) unsigned NOT NULL auto_increment,
  `task_id` int(10) unsigned NOT NULL default '0',
  `related_id` int(10) unsigned NOT NULL default '0',  
  PRIMARY KEY  (`id`),
  KEY `related_id` (`related_id`),
  KEY `task_id` (`task_id`)
) ENGINE=MyISAM DEFAULT CHARSET=utf8;

DROP TABLE IF EXISTS `project_related`;
CREATE TABLE `project_related` (
  `id` int(10) unsigned NOT NULL auto_increment,
  `project_id` int(10) unsigned NOT NULL default '0',
  `related_id` int(10) unsigned NOT NULL default '0',  
  PRIMARY KEY  (`id`),
  KEY `related_id` (`related_id`),
  KEY `project_id` (`project_id`)
) ENGINE=MyISAM DEFAULT CHARSET=utf8;

DROP TABLE IF EXISTS `event_document`;
CREATE TABLE `event_document` (
  `id` int(10) unsigned NOT NULL auto_increment,
  `event_id` int(10) unsigned NOT NULL default '0',
  `document_id` int(10) unsigned NOT NULL default '0',   
  PRIMARY KEY  (`id`),
  KEY `event_id` (`event_id`),
  KEY `document_id` (`document_id`)
) ENGINE=MyISAM DEFAULT CHARSET=utf8;

DROP TABLE IF EXISTS `project_document`;
CREATE TABLE `project_document` (
  `id` int(10) unsigned NOT NULL auto_increment,
  `project_id` int(10) unsigned NOT NULL default '0',
  `document_id` int(10) unsigned NOT NULL default '0',   
  PRIMARY KEY  (`id`),
  KEY `project_id` (`project_id`),
  KEY `document_id` (`document_id`)
) ENGINE=MyISAM DEFAULT CHARSET=utf8;

DROP TABLE IF EXISTS `contact_document`;
CREATE TABLE `contact_document` (
  `id` int(10) unsigned NOT NULL auto_increment,
  `contact_id` int(10) unsigned NOT NULL default '0',
  `document_id` int(10) unsigned NOT NULL default '0',   
  PRIMARY KEY  (`id`),
  KEY `contact_id` (`contact_id`),
  KEY `document_id` (`document_id`)
) ENGINE=MyISAM DEFAULT CHARSET=utf8;

DROP TABLE IF EXISTS `project_event`;
CREATE TABLE `project_event` (
  `id` int(10) unsigned NOT NULL auto_increment,
  `project_id` int(10) unsigned NOT NULL default '0',
  `event_id` int(10) unsigned NOT NULL default '0',   
  PRIMARY KEY  (`id`),
  KEY `project_id` (`project_id`),
  KEY `event_id` (`event_id`)
) ENGINE=MyISAM DEFAULT CHARSET=utf8;
        ]]></UpgradeSql>
    </Version>     
</Upgrade>